topsis_Manik_101903077/TOPSIS.py
topsis_Manik_101903077/__init__.py
Topsis_Manik_101903077-1.0.1.dist-info/LICENSE
Topsis_Manik_101903077-1.0.1.dist-info/METADATA
Topsis_Manik_101903077-1.0.1.dist-info/WHEEL
Topsis_Manik_101903077-1.0.1.dist-info/top_level.txt
Topsis_Manik_101903077-1.0.1.dist-info/RECORD
