Metadata-Version: 2.1
Name: Topsis-Manik-101903077
Version: 1.0.1
Summary: TOPSIS Implementation using Python
Author: Manik
Author-email: mmanik_be19@thapar.edu
License: UNKNOWN
Keywords: python,topsis python,topsis using command line,TOPSIS,topsis using python
Platform: UNKNOWN
Classifier: Development Status :: 1 - Planning
Classifier: Intended Audience :: Developers
Classifier: Programming Language :: Python :: 3
Classifier: Operating System :: Unix
Classifier: Operating System :: MacOS :: MacOS X
Classifier: Operating System :: Microsoft :: Windows
License-File: LICENSE
Requires-Dist: pandas
Requires-Dist: logging
